monkai_trace/__init__.py
monkai_trace/async_client.py
monkai_trace/client.py
monkai_trace/exceptions.py
monkai_trace/file_handlers.py
monkai_trace/models.py
monkai_trace/session_manager.py
monkai_trace/integrations/__init__.py
monkai_trace/integrations/langchain.py
monkai_trace/integrations/logging.py
monkai_trace/integrations/monkai_agent.py
monkai_trace/integrations/openai_agents.py
monkai_trace-0.2.9.dist-info/licenses/LICENSE
monkai_trace-0.2.9.dist-info/METADATA
monkai_trace-0.2.9.dist-info/WHEEL
monkai_trace-0.2.9.dist-info/top_level.txt
monkai_trace-0.2.9.dist-info/RECORD
