Metadata-Version: 2.4
Name: monkai-trace
Version: 0.2.9
Summary: Official Python SDK for MonkAI - Track and analyze your AI agent conversations
Author-email: MonkAI Team <support@monkai.ai>
License: MIT
Project-URL: Homepage, https://monkai.ai
Project-URL: Documentation, https://docs.monkai.ai
Project-URL: Repository, https://github.com/monkai/monkai-trace-python
Project-URL: Issues, https://github.com/monkai/monkai-trace-python/issues
Keywords: monkai,ai,agents,monitoring,observability,llm,openai
Classifier: Development Status :: 4 - Beta
Classifier: Intended Audience :: Developers
Classifier: License :: OSI Approved :: MIT License
Classifier: Programming Language :: Python :: 3
Classifier: Programming Language :: Python :: 3.8
Classifier: Programming Language :: Python :: 3.9
Classifier: Programming Language :: Python :: 3.10
Classifier: Programming Language :: Python :: 3.11
Classifier: Programming Language :: Python :: 3.12
Classifier: Topic :: Software Development :: Libraries :: Python Modules
Classifier: Topic :: Scientific/Engineering :: Artificial Intelligence
Requires-Python: >=3.8
License-File: LICENSE
Requires-Dist: requests>=2.31.0
Requires-Dist: pydantic>=2.0.0
Provides-Extra: openai-agents
Requires-Dist: openai-agents-python>=0.1.0; extra == "openai-agents"
Provides-Extra: dev
Requires-Dist: pytest>=7.4.0; extra == "dev"
Requires-Dist: pytest-cov>=4.1.0; extra == "dev"
Requires-Dist: pytest-asyncio>=0.21.0; extra == "dev"
Requires-Dist: black>=23.0.0; extra == "dev"
Requires-Dist: ruff>=0.1.0; extra == "dev"
Requires-Dist: mypy>=1.7.0; extra == "dev"
Requires-Dist: types-requests>=2.31.0; extra == "dev"
Dynamic: license-file
